setup.py
piprinter/__init__.py
piprinter/pi_printer.py
piprinter.egg-info/PKG-INFO
piprinter.egg-info/SOURCES.txt
piprinter.egg-info/dependency_links.txt
piprinter.egg-info/requires.txt
piprinter.egg-info/top_level.txt